MANIFEST.in
README.rst
setup.py
docs/HISTORY.rst
rer/__init__.py
rer.al.mcorevideoportlet.egg-info/PKG-INFO
rer.al.mcorevideoportlet.egg-info/SOURCES.txt
rer.al.mcorevideoportlet.egg-info/dependency_links.txt
rer.al.mcorevideoportlet.egg-info/entry_points.txt
rer.al.mcorevideoportlet.egg-info/namespace_packages.txt
rer.al.mcorevideoportlet.egg-info/not-zip-safe
rer.al.mcorevideoportlet.egg-info/requires.txt
rer.al.mcorevideoportlet.egg-info/top_level.txt
rer/al/__init__.py
rer/al/mcorevideoportlet/__init__.py
rer/al/mcorevideoportlet/build_18n_po.sh
rer/al/mcorevideoportlet/config.py
rer/al/mcorevideoportlet/configure.zcml
rer/al/mcorevideoportlet/video_portlet.pt
rer/al/mcorevideoportlet/video_portlet.py
rer/al/mcorevideoportlet/i18n/plone-it.po
rer/al/mcorevideoportlet/locales/rer.al.mcorevideoportlet.pot
rer/al/mcorevideoportlet/locales/it/LC_MESSAGES/rer.al.mcorevideoportlet.mo
rer/al/mcorevideoportlet/locales/it/LC_MESSAGES/rer.al.mcorevideoportlet.po
rer/al/mcorevideoportlet/profiles/default/metadata.xml
rer/al/mcorevideoportlet/profiles/default/portlets.xml