Metadata-Version: 1.1
Name: rer.al.mcorevideoportlet
Version: 2.1.1
Summary: This package is used to show mediacore video into a portlet
Home-page: https://github.com/PloneGov-IT/rer.al.mcorevideoportlet
Author: RedTurtle Technology
Author-email: sviluppoplone@redturtle.it
License: GPL
Keywords: plone video mediacore
Platform: UNKNOWN
Classifier: Programming Language :: Python
Classifier: Framework :: Plone :: 4.1
Classifier: Framework :: Plone :: 4.2
Classifier: License :: OSI Approved :: GNU General Public License (GPL)
